[
    {
        "symbol": "ADA-USDT",
        "lastPrice": "1.0207",
        "highPrice24h": "1.1641",
        "lowPrice24h": "0.8935",
        "changeRate": "-0.1188",
        "lastUpdated": "2024-12-10 06:34:53"
    },
    {
        "symbol": "ALGO-USDT",
        "lastPrice": "0.00011422",
        "highPrice24h": "0.00012401",
        "lowPrice24h": "0.00009961",
        "changeRate": "-0.0607",
        "lastUpdated": "2024-12-10 06:34:53"
    },
    {
        "symbol": "ATOM-USDT",
        "lastPrice": "0.00008754",
        "highPrice24h": "0.00009819",
        "lowPrice24h": "0.0000796",
        "changeRate": "-0.1084",
        "lastUpdated": "2024-12-10 06:34:53"
    },
    {
        "symbol": "AVAX-USDT",
        "lastPrice": "0.00046849",
        "highPrice24h": "0.00052098",
        "lowPrice24h": "0.0004169",
        "changeRate": "-0.0989",
        "lastUpdated": "2024-12-10 06:34:53"
    },
    {
        "symbol": "BCH-USDT",
        "lastPrice": "546.42",
        "highPrice24h": "613.25",
        "lowPrice24h": "487.28",
        "changeRate": "-0.0997",
        "lastUpdated": "2024-12-10 06:34:53"
    },
    {
        "symbol": "BTC-USDT",
        "lastPrice": "97300",
        "highPrice24h": "100416.5",
        "lowPrice24h": "94000",
        "changeRate": "-0.0176",
        "lastUpdated": "2024-12-10 06:34:53"
    },
    {
        "symbol": "CAKE-USDT",
        "lastPrice": "3.47",
        "highPrice24h": "3.998",
        "lowPrice24h": "2.78",
        "changeRate": "-0.1268",
        "lastUpdated": "2024-12-10 06:34:53"
    },
    {
        "symbol": "DASH-USDT",
        "lastPrice": "0.0004713",
        "highPrice24h": "0.0005667",
        "lowPrice24h": "0.0004274",
        "changeRate": "-0.1683",
        "lastUpdated": "2024-12-10 06:34:53"
    },
    {
        "symbol": "DGB-USDT",
        "lastPrice": "0.00000394",
        "highPrice24h": "0.00000446",
        "lowPrice24h": "0.00000323",
        "changeRate": "-0.1167",
        "lastUpdated": "2024-12-10 06:34:53"
    },
    {
        "symbol": "DOGE-USDT",
        "lastPrice": "0.41226",
        "highPrice24h": "0.44835",
        "lowPrice24h": "0.37",
        "changeRate": "-0.0748",
        "lastUpdated": "2024-12-10 06:34:53"
    },
    {
        "symbol": "DOT-USDT",
        "lastPrice": "8.6434",
        "highPrice24h": "9.9865",
        "lowPrice24h": "7.2533",
        "changeRate": "-0.1296",
        "lastUpdated": "2024-12-10 06:34:53"
    },
    {
        "symbol": "EOS-USDT",
        "lastPrice": "1.0605",
        "highPrice24h": "1.2523",
        "lowPrice24h": "0.9091",
        "changeRate": "-0.1486",
        "lastUpdated": "2024-12-10 06:34:53"
    },
    {
        "symbol": "ETC-USDT",
        "lastPrice": "31.5311",
        "highPrice24h": "35.6234",
        "lowPrice24h": "27.6896",
        "changeRate": "-0.1117",
        "lastUpdated": "2024-12-10 06:34:53"
    },
    {
        "symbol": "ETH-USDT",
        "lastPrice": "3736.72",
        "highPrice24h": "3925.17",
        "lowPrice24h": "3483.6",
        "changeRate": "-0.0473",
        "lastUpdated": "2024-12-10 06:34:53"
    },
    {
        "symbol": "LINK-USDT",
        "lastPrice": "0.00024",
        "highPrice24h": "0.0002675",
        "lowPrice24h": "0.00020626",
        "changeRate": "-0.0936",
        "lastUpdated": "2024-12-10 06:34:53"
    },
    {
        "symbol": "LTC-USDT",
        "lastPrice": "0.030547",
        "highPrice24h": "0.032742",
        "lowPrice24h": "0.025944",
        "changeRate": "-0.067",
        "lastUpdated": "2024-12-10 06:34:53"
    },
    {
        "symbol": "QTUM-USDT",
        "lastPrice": "4.024",
        "highPrice24h": "4.697",
        "lowPrice24h": "3.319",
        "changeRate": "-0.1398",
        "lastUpdated": "2024-12-10 06:34:53"
    },
    {
        "symbol": "RVN-USDT",
        "lastPrice": "0.02574",
        "highPrice24h": "0.03078",
        "lowPrice24h": "0.02267",
        "changeRate": "-0.1615",
        "lastUpdated": "2024-12-10 06:34:53"
    },
    {
        "symbol": "SHIB-USDT",
        "lastPrice": "0.00006471",
        "highPrice24h": "0.00007026",
        "lowPrice24h": "0.00006273",
        "changeRate": "-0.0666",
        "lastUpdated": "2024-12-10 06:34:53"
    },
    {
        "symbol": "SOL-USDT",
        "lastPrice": "218.367",
        "highPrice24h": "232.331",
        "lowPrice24h": "200.88",
        "changeRate": "-0.0535",
        "lastUpdated": "2024-12-10 06:34:53"
    },
    {
        "symbol": "TRX-USDT",
        "lastPrice": "0.2636",
        "highPrice24h": "0.3056",
        "lowPrice24h": "0.2376",
        "changeRate": "-0.1348",
        "lastUpdated": "2024-12-10 06:34:53"
    },
    {
        "symbol": "UNI-USDT",
        "lastPrice": "15.907",
        "highPrice24h": "17.9938",
        "lowPrice24h": "13.7213",
        "changeRate": "-0.1159",
        "lastUpdated": "2024-12-10 06:34:53"
    },
    {
        "symbol": "XLM-USDT",
        "lastPrice": "0.00000424",
        "highPrice24h": "0.00000479",
        "lowPrice24h": "0.0000037",
        "changeRate": "-0.1103",
        "lastUpdated": "2024-12-10 06:34:53"
    },
    {
        "symbol": "XMR-USDT",
        "lastPrice": "0.04718",
        "highPrice24h": "0.05313",
        "lowPrice24h": "0.04286",
        "changeRate": "-0.1119",
        "lastUpdated": "2024-12-10 06:34:53"
    },
    {
        "symbol": "XRP-USDT",
        "lastPrice": "2.21662",
        "highPrice24h": "2.46441",
        "lowPrice24h": "1.97074",
        "changeRate": "-0.0952",
        "lastUpdated": "2024-12-10 06:34:53"
    }
]