[
    {
        "symbol": "ADA-USDT",
        "lastPrice": "0.2902",
        "highPrice24h": "0.3243",
        "lowPrice24h": "0.2685",
        "changeRate": "-0.1045",
        "lastUpdated": "2026-01-31 21:50:06"
    },
    {
        "symbol": "ALGO-USDT",
        "lastPrice": "0.00004246",
        "highPrice24h": "0.00004258",
        "lowPrice24h": "0.00004066",
        "changeRate": "0.0231",
        "lastUpdated": "2026-01-31 21:50:06"
    },
    {
        "symbol": "ATOM-USDT",
        "lastPrice": "0.00002475",
        "highPrice24h": "0.00002507",
        "lowPrice24h": "0.000024",
        "changeRate": "-0.0072",
        "lastUpdated": "2026-01-31 21:50:06"
    },
    {
        "symbol": "AVAX-USDT",
        "lastPrice": "0.00012749",
        "highPrice24h": "0.00012981",
        "lowPrice24h": "0.00012134",
        "changeRate": "-0.0113",
        "lastUpdated": "2026-01-31 21:50:06"
    },
    {
        "symbol": "BCH-USDT",
        "lastPrice": "489.36",
        "highPrice24h": "553.18",
        "lowPrice24h": "469",
        "changeRate": "-0.1153",
        "lastUpdated": "2026-01-31 21:50:06"
    },
    {
        "symbol": "BTC-USDT",
        "lastPrice": "78197.67",
        "highPrice24h": "84146.29",
        "lowPrice24h": "75708.45",
        "changeRate": "-0.0705",
        "lastUpdated": "2026-01-31 21:50:06"
    },
    {
        "symbol": "CAKE-USDT",
        "lastPrice": "1.512",
        "highPrice24h": "1.711",
        "lowPrice24h": "1.419",
        "changeRate": "-0.1121",
        "lastUpdated": "2026-01-31 21:50:06"
    },
    {
        "symbol": "DASH-USDT",
        "lastPrice": "0.0005581",
        "highPrice24h": "0.0006144",
        "lowPrice24h": "0.0005454",
        "changeRate": "-0.0781",
        "lastUpdated": "2026-01-31 21:50:06"
    },
    {
        "symbol": "DGB-USDT",
        "lastPrice": "0.00505",
        "highPrice24h": "0.005542",
        "lowPrice24h": "0.004727",
        "changeRate": "-0.0725",
        "lastUpdated": "2026-01-31 21:50:06"
    },
    {
        "symbol": "DOGE-USDT",
        "lastPrice": "0.10259",
        "highPrice24h": "0.11615",
        "lowPrice24h": "0.09483",
        "changeRate": "-0.1162",
        "lastUpdated": "2026-01-31 21:50:06"
    },
    {
        "symbol": "DOT-USDT",
        "lastPrice": "1.5248",
        "highPrice24h": "1.6999",
        "lowPrice24h": "1.4",
        "changeRate": "-0.1006",
        "lastUpdated": "2026-01-31 21:50:06"
    },
    {
        "symbol": "ETC-USDT",
        "lastPrice": "9.6053",
        "highPrice24h": "10.6675",
        "lowPrice24h": "9.0309",
        "changeRate": "-0.0971",
        "lastUpdated": "2026-01-31 21:50:06"
    },
    {
        "symbol": "ETH-USDT",
        "lastPrice": "2393.68",
        "highPrice24h": "2713.9",
        "lowPrice24h": "2246.88",
        "changeRate": "-0.1137",
        "lastUpdated": "2026-01-31 21:50:06"
    },
    {
        "symbol": "LINK-USDT",
        "lastPrice": "0.00012548",
        "highPrice24h": "0.0001287",
        "lowPrice24h": "0.00011881",
        "changeRate": "-0.0186",
        "lastUpdated": "2026-01-31 21:50:06"
    },
    {
        "symbol": "LTC-USDT",
        "lastPrice": "0.02447",
        "highPrice24h": "0.02478",
        "lowPrice24h": "0.02367",
        "changeRate": "0.0111",
        "lastUpdated": "2026-01-31 21:50:06"
    },
    {
        "symbol": "QTUM-USDT",
        "lastPrice": "1.039",
        "highPrice24h": "1.173",
        "lowPrice24h": "0.997",
        "changeRate": "-0.1081",
        "lastUpdated": "2026-01-31 21:50:06"
    },
    {
        "symbol": "RVN-USDT",
        "lastPrice": "0.00608",
        "highPrice24h": "0.00688",
        "lowPrice24h": "0.00558",
        "changeRate": "-0.1162",
        "lastUpdated": "2026-01-31 21:50:06"
    },
    {
        "symbol": "SHIB-USDT",
        "lastPrice": "0.000065",
        "highPrice24h": "0.000065",
        "lowPrice24h": "0.00006217",
        "changeRate": "0.0333",
        "lastUpdated": "2026-01-31 21:50:06"
    },
    {
        "symbol": "SOL-USDT",
        "lastPrice": "11.476",
        "highPrice24h": "11.713",
        "lowPrice24h": "10.838",
        "changeRate": "-0.0027",
        "lastUpdated": "2026-01-31 21:50:06"
    },
    {
        "symbol": "TRX-USDT",
        "lastPrice": "0.286",
        "highPrice24h": "0.2944",
        "lowPrice24h": "0.2841",
        "changeRate": "-0.0275",
        "lastUpdated": "2026-01-31 21:50:06"
    },
    {
        "symbol": "UNI-USDT",
        "lastPrice": "3.8944",
        "highPrice24h": "4.3072",
        "lowPrice24h": "3.6012",
        "changeRate": "-0.0879",
        "lastUpdated": "2026-01-31 21:50:06"
    },
    {
        "symbol": "XLM-USDT",
        "lastPrice": "0.00000226",
        "highPrice24h": "0.00000229",
        "lowPrice24h": "0.00000217",
        "changeRate": "-0.007",
        "lastUpdated": "2026-01-31 21:50:06"
    },
    {
        "symbol": "XMR-USDT",
        "lastPrice": "0.19204",
        "highPrice24h": "0.19376",
        "lowPrice24h": "0.16953",
        "changeRate": "0.1171",
        "lastUpdated": "2026-01-31 21:50:06"
    },
    {
        "symbol": "XRP-USDT",
        "lastPrice": "1.6197",
        "highPrice24h": "1.7379",
        "lowPrice24h": "1.5079",
        "changeRate": "-0.0617",
        "lastUpdated": "2026-01-31 21:50:06"
    }
]