[
    {
        "symbol": "ADA-USDT",
        "lastPrice": "0.05216",
        "highPrice24h": "0.05452",
        "lowPrice24h": "0.05176",
        "changeRate": "-0.0376",
        "lastUpdated": "2025-07-04 14:25:53"
    },
    {
        "symbol": "ALGO-USDT",
        "lastPrice": "0.00006863",
        "highPrice24h": "0.00007183",
        "lowPrice24h": "0.00006858",
        "changeRate": "-0.0362",
        "lastUpdated": "2025-07-04 14:25:53"
    },
    {
        "symbol": "ATOM-USDT",
        "lastPrice": "0.00003746",
        "highPrice24h": "0.00003866",
        "lowPrice24h": "0.00003715",
        "changeRate": "-0.0254",
        "lastUpdated": "2025-07-04 14:25:53"
    },
    {
        "symbol": "AVAX-USDT",
        "lastPrice": "0.00016639",
        "highPrice24h": "0.0001724",
        "lowPrice24h": "0.00016521",
        "changeRate": "-0.0262",
        "lastUpdated": "2025-07-04 14:25:53"
    },
    {
        "symbol": "BCH-USDT",
        "lastPrice": "0.004445",
        "highPrice24h": "0.004554",
        "lowPrice24h": "0.004192",
        "changeRate": "-0.0239",
        "lastUpdated": "2025-07-04 14:25:53"
    },
    {
        "symbol": "BTC-USDT",
        "lastPrice": "108036.6",
        "highPrice24h": "110277.7",
        "lowPrice24h": "107554.3",
        "changeRate": "-0.0203",
        "lastUpdated": "2025-07-04 14:25:53"
    },
    {
        "symbol": "CAKE-USDT",
        "lastPrice": "2.268",
        "highPrice24h": "2.351",
        "lowPrice24h": "2.249",
        "changeRate": "-0.0353",
        "lastUpdated": "2025-07-04 14:25:53"
    },
    {
        "symbol": "DASH-USDT",
        "lastPrice": "0.0001858",
        "highPrice24h": "0.0001884",
        "lowPrice24h": "0.000183",
        "changeRate": "-0.0138",
        "lastUpdated": "2025-07-04 14:25:53"
    },
    {
        "symbol": "DGB-USDT",
        "lastPrice": "0.00000296",
        "highPrice24h": "0.00000298",
        "lowPrice24h": "0.00000291",
        "changeRate": "0.014",
        "lastUpdated": "2025-07-04 14:25:53"
    },
    {
        "symbol": "DOGE-USDT",
        "lastPrice": "0.00000152",
        "highPrice24h": "0.00000158",
        "lowPrice24h": "0.00000152",
        "changeRate": "-0.0367",
        "lastUpdated": "2025-07-04 14:25:53"
    },
    {
        "symbol": "DOT-USDT",
        "lastPrice": "3.3901",
        "highPrice24h": "3.5919",
        "lowPrice24h": "3.3628",
        "changeRate": "-0.0561",
        "lastUpdated": "2025-07-04 14:25:53"
    },
    {
        "symbol": "EOS-USDT",
        "lastPrice": "0.7567",
        "highPrice24h": "0.7748",
        "lowPrice24h": "0.7208",
        "changeRate": "-0.0139",
        "lastUpdated": "2025-07-04 14:25:53"
    },
    {
        "symbol": "ETC-USDT",
        "lastPrice": "16.4239",
        "highPrice24h": "17.2546",
        "lowPrice24h": "16.3504",
        "changeRate": "-0.0481",
        "lastUpdated": "2025-07-04 14:25:53"
    },
    {
        "symbol": "ETH-USDT",
        "lastPrice": "2510.49",
        "highPrice24h": "2616.73",
        "lowPrice24h": "2510.49",
        "changeRate": "-0.0406",
        "lastUpdated": "2025-07-04 14:25:53"
    },
    {
        "symbol": "LINK-USDT",
        "lastPrice": "0.00012216",
        "highPrice24h": "0.0001262",
        "lowPrice24h": "0.00012149",
        "changeRate": "-0.032",
        "lastUpdated": "2025-07-04 14:25:53"
    },
    {
        "symbol": "LTC-USDT",
        "lastPrice": "0.034724",
        "highPrice24h": "0.03496",
        "lowPrice24h": "0.034023",
        "changeRate": "0.0011",
        "lastUpdated": "2025-07-04 14:25:53"
    },
    {
        "symbol": "QTUM-USDT",
        "lastPrice": "1.971",
        "highPrice24h": "2.062",
        "lowPrice24h": "1.971",
        "changeRate": "-0.0441",
        "lastUpdated": "2025-07-04 14:25:53"
    },
    {
        "symbol": "RVN-USDT",
        "lastPrice": "0.013",
        "highPrice24h": "0.01356",
        "lowPrice24h": "0.01291",
        "changeRate": "-0.0412",
        "lastUpdated": "2025-07-04 14:25:53"
    },
    {
        "symbol": "SHIB-USDT",
        "lastPrice": "0.00006991",
        "highPrice24h": "0.00006991",
        "lowPrice24h": "0.0000689",
        "changeRate": "0.0142",
        "lastUpdated": "2025-07-04 14:25:53"
    },
    {
        "symbol": "SOL-USDT",
        "lastPrice": "13.389",
        "highPrice24h": "13.955",
        "lowPrice24h": "13.377",
        "changeRate": "-0.0328",
        "lastUpdated": "2025-07-04 14:25:53"
    },
    {
        "symbol": "TRX-USDT",
        "lastPrice": "0.283",
        "highPrice24h": "0.288",
        "lowPrice24h": "0.283",
        "changeRate": "-0.0066",
        "lastUpdated": "2025-07-04 14:25:53"
    },
    {
        "symbol": "UNI-USDT",
        "lastPrice": "6.9765",
        "highPrice24h": "7.7982",
        "lowPrice24h": "6.8968",
        "changeRate": "-0.1053",
        "lastUpdated": "2025-07-04 14:25:53"
    },
    {
        "symbol": "XLM-USDT",
        "lastPrice": "0.0000022",
        "highPrice24h": "0.00000223",
        "lowPrice24h": "0.00000218",
        "changeRate": "-0.0108",
        "lastUpdated": "2025-07-04 14:25:53"
    },
    {
        "symbol": "XMR-USDT",
        "lastPrice": "0.002924",
        "highPrice24h": "0.002975",
        "lowPrice24h": "0.002848",
        "changeRate": "0.0037",
        "lastUpdated": "2025-07-04 14:25:53"
    },
    {
        "symbol": "XRP-USDT",
        "lastPrice": "0.0008829",
        "highPrice24h": "0.0008829",
        "lowPrice24h": "0.0008693",
        "changeRate": "0.0101",
        "lastUpdated": "2025-07-04 14:25:53"
    }
]