[
    {
        "symbol": "ADA-USDT",
        "lastPrice": "0.1888",
        "highPrice24h": "0.1996",
        "lowPrice24h": "0.1803",
        "changeRate": "0.0442",
        "lastUpdated": "2026-07-05 14:18:04"
    },
    {
        "symbol": "ALGO-USDT",
        "lastPrice": "0.00005069",
        "highPrice24h": "0.00005195",
        "lowPrice24h": "0.00005046",
        "changeRate": "0.0003",
        "lastUpdated": "2026-07-05 14:18:04"
    },
    {
        "symbol": "ATOM-USDT",
        "lastPrice": "0.00002482",
        "highPrice24h": "0.00002545",
        "lowPrice24h": "0.00002467",
        "changeRate": "-0.022",
        "lastUpdated": "2026-07-05 14:18:04"
    },
    {
        "symbol": "AVAX-USDT",
        "lastPrice": "0.00010971",
        "highPrice24h": "0.00011213",
        "lowPrice24h": "0.00010782",
        "changeRate": "-0.0037",
        "lastUpdated": "2026-07-05 14:18:04"
    },
    {
        "symbol": "BCH-USDT",
        "lastPrice": "241.62",
        "highPrice24h": "242.1",
        "lowPrice24h": "228.37",
        "changeRate": "0.0494",
        "lastUpdated": "2026-07-05 14:18:04"
    },
    {
        "symbol": "BTC-USDT",
        "lastPrice": "62797.94",
        "highPrice24h": "63434.22",
        "lowPrice24h": "62608.79",
        "changeRate": "0.003",
        "lastUpdated": "2026-07-05 14:18:04"
    },
    {
        "symbol": "CAKE-USDT",
        "lastPrice": "1.419",
        "highPrice24h": "1.435",
        "lowPrice24h": "1.366",
        "changeRate": "0.0215",
        "lastUpdated": "2026-07-05 14:18:04"
    },
    {
        "symbol": "DASH-USDT",
        "lastPrice": "0.0005583",
        "highPrice24h": "0.0005959",
        "lowPrice24h": "0.0005527",
        "changeRate": "-0.0139",
        "lastUpdated": "2026-07-05 14:18:04"
    },
    {
        "symbol": "DGB-USDT",
        "lastPrice": "0.002528",
        "highPrice24h": "0.00278",
        "lowPrice24h": "0.002478",
        "changeRate": "0.0023",
        "lastUpdated": "2026-07-05 14:18:04"
    },
    {
        "symbol": "DOGE-USDT",
        "lastPrice": "0.07656",
        "highPrice24h": "0.07928",
        "lowPrice24h": "0.07531",
        "changeRate": "-0.0121",
        "lastUpdated": "2026-07-05 14:18:04"
    },
    {
        "symbol": "DOT-USDT",
        "lastPrice": "0.8734",
        "highPrice24h": "0.8998",
        "lowPrice24h": "0.8601",
        "changeRate": "-0.0043",
        "lastUpdated": "2026-07-05 14:18:04"
    },
    {
        "symbol": "ETC-USDT",
        "lastPrice": "7.0928",
        "highPrice24h": "7.3829",
        "lowPrice24h": "7.0438",
        "changeRate": "-0.024",
        "lastUpdated": "2026-07-05 14:18:04"
    },
    {
        "symbol": "ETH-USDT",
        "lastPrice": "0.0282",
        "highPrice24h": "0.02856",
        "lowPrice24h": "0.02802",
        "changeRate": "-0.0021",
        "lastUpdated": "2026-07-05 14:18:04"
    },
    {
        "symbol": "LINK-USDT",
        "lastPrice": "0.00012624",
        "highPrice24h": "0.00012919",
        "lowPrice24h": "0.0001253",
        "changeRate": "-0.0092",
        "lastUpdated": "2026-07-05 14:18:04"
    },
    {
        "symbol": "LTC-USDT",
        "lastPrice": "0.0254",
        "highPrice24h": "0.02551",
        "lowPrice24h": "0.0249",
        "changeRate": "0.0107",
        "lastUpdated": "2026-07-05 14:18:04"
    },
    {
        "symbol": "QTUM-USDT",
        "lastPrice": "0.708",
        "highPrice24h": "0.724",
        "lowPrice24h": "0.705",
        "changeRate": "-0.0084",
        "lastUpdated": "2026-07-05 14:18:04"
    },
    {
        "symbol": "RVN-USDT",
        "lastPrice": "0.00377",
        "highPrice24h": "0.00399",
        "lowPrice24h": "0.00377",
        "changeRate": "-0.0333",
        "lastUpdated": "2026-07-05 14:18:04"
    },
    {
        "symbol": "SHIB-USDT",
        "lastPrice": "0.0000568",
        "highPrice24h": "0.0000582",
        "lowPrice24h": "0.00005679",
        "changeRate": "-0.024",
        "lastUpdated": "2026-07-05 14:18:04"
    },
    {
        "symbol": "SOL-USDT",
        "lastPrice": "11.369",
        "highPrice24h": "11.533",
        "lowPrice24h": "11.249",
        "changeRate": "-0.0138",
        "lastUpdated": "2026-07-05 14:18:04"
    },
    {
        "symbol": "TRX-USDT",
        "lastPrice": "0.3296",
        "highPrice24h": "0.3297",
        "lowPrice24h": "0.3242",
        "changeRate": "0.0119",
        "lastUpdated": "2026-07-05 14:18:04"
    },
    {
        "symbol": "UNI-USDT",
        "lastPrice": "3.1298",
        "highPrice24h": "3.2831",
        "lowPrice24h": "3.1",
        "changeRate": "-0.0274",
        "lastUpdated": "2026-07-05 14:18:04"
    },
    {
        "symbol": "XLM-USDT",
        "lastPrice": "0.0000032",
        "highPrice24h": "0.00000343",
        "lowPrice24h": "0.00000316",
        "changeRate": "-0.0223",
        "lastUpdated": "2026-07-05 14:18:04"
    },
    {
        "symbol": "XMR-USDT",
        "lastPrice": "0.1856",
        "highPrice24h": "0.18887",
        "lowPrice24h": "0.18122",
        "changeRate": "-0.0133",
        "lastUpdated": "2026-07-05 14:18:04"
    },
    {
        "symbol": "XRP-USDT",
        "lastPrice": "1.1339",
        "highPrice24h": "1.181",
        "lowPrice24h": "1.1291",
        "changeRate": "-0.0232",
        "lastUpdated": "2026-07-05 14:18:04"
    }
]