[
    {
        "symbol": "ADA-USDT",
        "lastPrice": "0.3396",
        "highPrice24h": "0.3477",
        "lowPrice24h": "0.3339",
        "changeRate": "-0.021",
        "lastUpdated": "2024-10-10 01:47:40"
    },
    {
        "symbol": "ALGO-USDT",
        "lastPrice": "0.00004973",
        "highPrice24h": "0.00005072",
        "lowPrice24h": "0.00004901",
        "changeRate": "-0.0024",
        "lastUpdated": "2024-10-10 01:47:40"
    },
    {
        "symbol": "ATOM-USDT",
        "lastPrice": "0.00007013",
        "highPrice24h": "0.00007077",
        "lowPrice24h": "0.00006883",
        "changeRate": "0.006",
        "lastUpdated": "2024-10-10 01:47:40"
    },
    {
        "symbol": "AVAX-USDT",
        "lastPrice": "0.00042577",
        "highPrice24h": "0.00042962",
        "lowPrice24h": "0.00041653",
        "changeRate": "-0.0029",
        "lastUpdated": "2024-10-10 01:47:40"
    },
    {
        "symbol": "BCH-USDT",
        "lastPrice": "320.55",
        "highPrice24h": "328.62",
        "lowPrice24h": "317.98",
        "changeRate": "-0.0213",
        "lastUpdated": "2024-10-10 01:47:40"
    },
    {
        "symbol": "BTC-USDT",
        "lastPrice": "60760.2",
        "highPrice24h": "62515.1",
        "lowPrice24h": "60280.9",
        "changeRate": "-0.0266",
        "lastUpdated": "2024-10-10 01:47:40"
    },
    {
        "symbol": "CAKE-USDT",
        "lastPrice": "1.844",
        "highPrice24h": "1.911",
        "lowPrice24h": "1.81",
        "changeRate": "-0.0253",
        "lastUpdated": "2024-10-10 01:47:40"
    },
    {
        "symbol": "DASH-USDT",
        "lastPrice": "0.0003763",
        "highPrice24h": "0.0003763",
        "lowPrice24h": "0.0003703",
        "changeRate": "0.0083",
        "lastUpdated": "2024-10-10 01:47:40"
    },
    {
        "symbol": "DGB-USDT",
        "lastPrice": "0.00000268",
        "highPrice24h": "0.00000274",
        "lowPrice24h": "0.00000262",
        "changeRate": "-0.0085",
        "lastUpdated": "2024-10-10 01:47:40"
    },
    {
        "symbol": "DOGE-USDT",
        "lastPrice": "0.10756",
        "highPrice24h": "0.1114",
        "lowPrice24h": "0.10609",
        "changeRate": "-0.0105",
        "lastUpdated": "2024-10-10 01:47:40"
    },
    {
        "symbol": "DOT-USDT",
        "lastPrice": "4.0448",
        "highPrice24h": "4.1483",
        "lowPrice24h": "3.9524",
        "changeRate": "-0.0215",
        "lastUpdated": "2024-10-10 01:47:40"
    },
    {
        "symbol": "EOS-USDT",
        "lastPrice": "0.4584",
        "highPrice24h": "0.472",
        "lowPrice24h": "0.4512",
        "changeRate": "-0.0275",
        "lastUpdated": "2024-10-10 01:47:40"
    },
    {
        "symbol": "ETC-USDT",
        "lastPrice": "18.2463",
        "highPrice24h": "18.505",
        "lowPrice24h": "17.9289",
        "changeRate": "-0.0139",
        "lastUpdated": "2024-10-10 01:47:40"
    },
    {
        "symbol": "ETH-USDT",
        "lastPrice": "2373.24",
        "highPrice24h": "2463.32",
        "lowPrice24h": "2359.59",
        "changeRate": "-0.0304",
        "lastUpdated": "2024-10-10 01:47:40"
    },
    {
        "symbol": "LINK-USDT",
        "lastPrice": "0.0001742",
        "highPrice24h": "0.00017528",
        "lowPrice24h": "0.00017085",
        "changeRate": "-0.0061",
        "lastUpdated": "2024-10-10 01:47:40"
    },
    {
        "symbol": "LTC-USDT",
        "lastPrice": "0.027188",
        "highPrice24h": "0.027292",
        "lowPrice24h": "0.026499",
        "changeRate": "0.0191",
        "lastUpdated": "2024-10-10 01:47:40"
    },
    {
        "symbol": "QTUM-USDT",
        "lastPrice": "0.00003831",
        "highPrice24h": "0.00003883",
        "lowPrice24h": "0.00003748",
        "changeRate": "-0.0095",
        "lastUpdated": "2024-10-10 01:47:40"
    },
    {
        "symbol": "RVN-USDT",
        "lastPrice": "0.01623",
        "highPrice24h": "0.01656",
        "lowPrice24h": "0.01591",
        "changeRate": "-0.0193",
        "lastUpdated": "2024-10-10 01:47:40"
    },
    {
        "symbol": "SHIB-USDT",
        "lastPrice": "0.00015822",
        "highPrice24h": "0.00016337",
        "lowPrice24h": "0.00015625",
        "changeRate": "-0.0209",
        "lastUpdated": "2024-10-10 01:47:40"
    },
    {
        "symbol": "SOL-USDT",
        "lastPrice": "139.763",
        "highPrice24h": "145.025",
        "lowPrice24h": "137.684",
        "changeRate": "-0.0341",
        "lastUpdated": "2024-10-10 01:47:40"
    },
    {
        "symbol": "TRX-USDT",
        "lastPrice": "0.1598",
        "highPrice24h": "0.1621",
        "lowPrice24h": "0.1595",
        "changeRate": "0.0012",
        "lastUpdated": "2024-10-10 01:47:40"
    },
    {
        "symbol": "UNI-USDT",
        "lastPrice": "7.3906",
        "highPrice24h": "7.4139",
        "lowPrice24h": "7.0643",
        "changeRate": "0.0258",
        "lastUpdated": "2024-10-10 01:47:40"
    },
    {
        "symbol": "XLM-USDT",
        "lastPrice": "0.00000148",
        "highPrice24h": "0.00000148",
        "lowPrice24h": "0.00000144",
        "changeRate": "0.0165",
        "lastUpdated": "2024-10-10 01:47:40"
    },
    {
        "symbol": "XMR-USDT",
        "lastPrice": "0.06274",
        "highPrice24h": "0.06356",
        "lowPrice24h": "0.06076",
        "changeRate": "0.031",
        "lastUpdated": "2024-10-10 01:47:40"
    },
    {
        "symbol": "XRP-USDT",
        "lastPrice": "0.526",
        "highPrice24h": "0.53412",
        "lowPrice24h": "0.52096",
        "changeRate": "-0.0152",
        "lastUpdated": "2024-10-10 01:47:40"
    }
]